clickhouse_types/__init__.py
clickhouse_types/_utils.py
clickhouse_types/pyarrow.py
clickhouse_types/sqlalchemy/__init__.py
clickhouse_types/sqlalchemy/base.py
clickhouse_types/sqlalchemy/common.py
clickhouse_types/sqlalchemy/ip.py
clickhouse_types/sqlalchemy/nested.py
clickhouse_types/sqlalchemy.py
clickhouse_types-0.1.1.dist-info/LICENSE.txt
clickhouse_types-0.1.1.dist-info/METADATA
clickhouse_types-0.1.1.dist-info/WHEEL
clickhouse_types-0.1.1.dist-info/RECORD
