Metadata-Version: 2.1
Name: clickhouse-types
Version: 0.1.1
Summary: Converting ClickHouse types into other schemas' types
Author: Cheng Chang
Author-email: cheng.chang3459@gmail.com
Requires-Python: >=3.7
Classifier: Programming Language :: Python :: 3
Classifier: Programming Language :: Python :: 3.7
Classifier: Programming Language :: Python :: 3.8
Classifier: Programming Language :: Python :: 3.9
Classifier: Programming Language :: Python :: 3.10
Classifier: Programming Language :: Python :: 3.11
Classifier: Programming Language :: Python :: 3.12
Classifier: Programming Language :: Python :: 3.13
